fastmail_cli/__init__.py
fastmail_cli/__main__.py
fastmail_cli/cli.py
fastmail_cli/jmapc.py
fastmail_cli-0.2.1.dist-info/METADATA
fastmail_cli-0.2.1.dist-info/WHEEL
fastmail_cli-0.2.1.dist-info/entry_points.txt
fastmail_cli-0.2.1.dist-info/licenses/LICENSE
fastmail_cli-0.2.1.dist-info/RECORD
