Metadata-Version: 2.4
Name: fastmail-cli
Version: 0.2.1
Summary: CLI for AI agents to access Fastmail via JMAP - draft responses without sending
Project-URL: Homepage, https://github.com/noc0dev/fastmail-cli
Project-URL: Repository, https://github.com/noc0dev/fastmail-cli
Project-URL: Issues, https://github.com/noc0dev/fastmail-cli/issues
Author-email: Joseph Turian <lastname@gmail.com>
License-Expression: Apache-2.0
License-File: LICENSE
Keywords: api,cli,email,fastmail,jmap
Classifier: Development Status :: 3 - Alpha
Classifier: Environment :: Console
Classifier: Intended Audience :: Developers
Classifier: License :: OSI Approved :: Apache Software License
Classifier: Operating System :: OS Independent
Classifier: Programming Language :: Python :: 3
Classifier: Programming Language :: Python :: 3.13
Classifier: Topic :: Communications :: Email
Classifier: Topic :: Utilities
Requires-Python: >=3.13
Requires-Dist: jmapc>=0.2.23
